[
  {
    "recognitionModel": "recognition_01",
    "faceRectangle": {
      "width": 344,
      "height": 410,
      "left": 1436,
      "top": 233
    },
    "faceLandmarks": {
      "pupilLeft": {
        "x": 1577.1,
        "y": 380.9
      },
      "pupilRight": {
        "x": 1693.5,
        "y": 444.3
      },
      "noseTip": {
        "x": 1611.9,
        "y": 496.6
      },
      "mouthLeft": {
        "x": 1517.3,
        "y": 511.9
      },
      "mouthRight": {
        "x": 1627.5,
        "y": 567.3
      },
      "eyebrowLeftOuter": {
        "x": 1551.9,
        "y": 318.9
      },
      "eyebrowLeftInner": {
        "x": 1631.1,
        "y": 357.8
      },
      "eyeLeftOuter": {
        "x": 1554,
        "y": 367.6
      },
      "eyeLeftTop": {
        "x": 1585.5,
        "y": 372.5
      },
      "eyeLeftBottom": {
        "x": 1570.5,
        "y": 388.3
      },
      "eyeLeftInner": {
        "x": 1598.6,
        "y": 395.2
      },
      "eyebrowRightInner": {
        "x": 1691.2,
        "y": 394.8
      },
      "eyebrowRightOuter": {
        "x": 1752.6,
        "y": 430.8
      },
      "eyeRightInner": {
        "x": 1671.1,
        "y": 437.2
      },
      "eyeRightTop": {
        "x": 1697.9,
        "y": 432.3
      },
      "eyeRightBottom": {
        "x": 1690.4,
        "y": 453.3
      },
      "eyeRightOuter": {
        "x": 1714.5,
        "y": 454.3
      },
      "noseRootLeft": {
        "x": 1619.4,
        "y": 414.2
      },
      "noseRootRight": {
        "x": 1652.6,
        "y": 432.7
      },
      "noseLeftAlarTop": {
        "x": 1586.9,
        "y": 459.7
      },
      "noseRightAlarTop": {
        "x": 1642.4,
        "y": 486.4
      },
      "noseLeftAlarOutTip": {
        "x": 1561.7,
        "y": 477.2
      },
      "noseRightAlarOutTip": {
        "x": 1639.4,
        "y": 517.2
      },
      "upperLipTop": {
        "x": 1585.6,
        "y": 540.2
      },
      "upperLipBottom": {
        "x": 1578.6,
        "y": 547.8
      },
      "underLipTop": {
        "x": 1574.7,
        "y": 555.3
      },
      "underLipBottom": {
        "x": 1567.3,
        "y": 570.4
      }
    },
    "faceAttributes": {
      "mask": {
        "type": "noMask",
        "noseAndMouthCovered": false
      }
    }
  },
  {
    "recognitionModel": "recognition_01",
    "faceRectangle": {
      "width": 250,
      "height": 293,
      "left": 2228,
      "top": 1026
    },
    "faceLandmarks": {
      "pupilLeft": {
        "x": 2313.6,
        "y": 1116.9
      },
      "pupilRight": {
        "x": 2418.3,
        "y": 1154.4
      },
      "noseTip": {
        "x": 2350.5,
        "y": 1178.2
      },
      "mouthLeft": {
        "x": 2281.4,
        "y": 1211.6
      },
      "mouthRight": {
        "x": 2379.7,
        "y": 1247.5
      },
      "eyebrowLeftOuter": {
        "x": 2291.2,
        "y": 1072.6
      },
      "eyebrowLeftInner": {
        "x": 2350.1,
        "y": 1089.1
      },
      "eyeLeftOuter": {
        "x": 2293.9,
        "y": 1110.6
      },
      "eyeLeftTop": {
        "x": 2318.5,
        "y": 1109.8
      },
      "eyeLeftBottom": {
        "x": 2309.3,
        "y": 1122
      },
      "eyeLeftInner": {
        "x": 2332.8,
        "y": 1125
      },
      "eyebrowRightInner": {
        "x": 2406.6,
        "y": 1111
      },
      "eyebrowRightOuter": {
        "x": 2464.1,
        "y": 1141.3
      },
      "eyeRightInner": {
        "x": 2398.7,
        "y": 1149.8
      },
      "eyeRightTop": {
        "x": 2419.7,
        "y": 1144.9
      },
      "eyeRightBottom": {
        "x": 2417.2,
        "y": 1161
      },
      "eyeRightOuter": {
        "x": 2437.6,
        "y": 1162.2
      },
      "noseRootLeft": {
        "x": 2349.6,
        "y": 1132.6
      },
      "noseRootRight": {
        "x": 2379.7,
        "y": 1141.9
      },
      "noseLeftAlarTop": {
        "x": 2330.7,
        "y": 1160.6
      },
      "noseRightAlarTop": {
        "x": 2376.7,
        "y": 1177
      },
      "noseLeftAlarOutTip": {
        "x": 2313.7,
        "y": 1174.8
      },
      "noseRightAlarOutTip": {
        "x": 2379.9,
        "y": 1200.2
      },
      "upperLipTop": {
        "x": 2337.8,
        "y": 1217.6
      },
      "upperLipBottom": {
        "x": 2332.4,
        "y": 1225.7
      },
      "underLipTop": {
        "x": 2325.2,
        "y": 1244.4
      },
      "underLipBottom": {
        "x": 2320.2,
        "y": 1258.5
      }
    },
    "faceAttributes": {
      "mask": {
        "type": "noMask",
        "noseAndMouthCovered": false
      }
    }
  },
  {
    "recognitionModel": "recognition_01",
    "faceRectangle": {
      "width": 228,
      "height": 313,
      "left": 2447,
      "top": 519
    },
    "faceLandmarks": {
      "pupilLeft": {
        "x": 2516.8,
        "y": 639
      },
      "pupilRight": {
        "x": 2618.1,
        "y": 664.2
      },
      "noseTip": {
        "x": 2549.1,
        "y": 694.2
      },
      "mouthLeft": {
        "x": 2489.7,
        "y": 732.1
      },
      "mouthRight": {
        "x": 2595,
        "y": 759
      },
      "eyebrowLeftOuter": {
        "x": 2495.5,
        "y": 605.6
      },
      "eyebrowLeftInner": {
        "x": 2544.8,
        "y": 615.8
      },
      "eyeLeftOuter": {
        "x": 2498.9,
        "y": 635.5
      },
      "eyeLeftTop": {
        "x": 2520.2,
        "y": 633.7
      },
      "eyeLeftBottom": {
        "x": 2513.6,
        "y": 642
      },
      "eyeLeftInner": {
        "x": 2534.7,
        "y": 644.9
      },
      "eyebrowRightInner": {
        "x": 2598.4,
        "y": 630.8
      },
      "eyebrowRightOuter": {
        "x": 2657.6,
        "y": 652.8
      },
      "eyeRightInner": {
        "x": 2599.6,
        "y": 661.5
      },
      "eyeRightTop": {
        "x": 2617.6,
        "y": 656.9
      },
      "eyeRightBottom": {
        "x": 2618.1,
        "y": 668.6
      },
      "eyeRightOuter": {
        "x": 2637.1,
        "y": 669.7
      },
      "noseRootLeft": {
        "x": 2548.2,
        "y": 651.5
      },
      "noseRootRight": {
        "x": 2578.2,
        "y": 658
      },
      "noseLeftAlarTop": {
        "x": 2530.4,
        "y": 678.9
      },
      "noseRightAlarTop": {
        "x": 2579,
        "y": 691.1
      },
      "noseLeftAlarOutTip": {
        "x": 2516.1,
        "y": 694
      },
      "noseRightAlarOutTip": {
        "x": 2584.9,
        "y": 712.9
      },
      "upperLipTop": {
        "x": 2544,
        "y": 736.3
      },
      "upperLipBottom": {
        "x": 2539.7,
        "y": 742.8
      },
      "underLipTop": {
        "x": 2534.6,
        "y": 761.5
      },
      "underLipBottom": {
        "x": 2531.6,
        "y": 773.8
      }
    },
    "faceAttributes": {
      "mask": {
        "type": "noMask",
        "noseAndMouthCovered": false
      }
    }
  },
  {
    "recognitionModel": "recognition_01",
    "faceRectangle": {
      "width": 238,
      "height": 276,
      "left": 2716,
      "top": 1166
    },
    "faceLandmarks": {
      "pupilLeft": {
        "x": 2781.1,
        "y": 1268.4
      },
      "pupilRight": {
        "x": 2883.7,
        "y": 1279.8
      },
      "noseTip": {
        "x": 2822.5,
        "y": 1319.8
      },
      "mouthLeft": {
        "x": 2769.4,
        "y": 1356.2
      },
      "mouthRight": {
        "x": 2873.9,
        "y": 1368.3
      },
      "eyebrowLeftOuter": {
        "x": 2746.8,
        "y": 1244.7
      },
      "eyebrowLeftInner": {
        "x": 2807.6,
        "y": 1247.9
      },
      "eyeLeftOuter": {
        "x": 2764.6,
        "y": 1267.4
      },
      "eyeLeftTop": {
        "x": 2782.2,
        "y": 1262.6
      },
      "eyeLeftBottom": {
        "x": 2780,
        "y": 1272.7
      },
      "eyeLeftInner": {
        "x": 2797.5,
        "y": 1270.8
      },
      "eyebrowRightInner": {
        "x": 2858.9,
        "y": 1253.5
      },
      "eyebrowRightOuter": {
        "x": 2924.1,
        "y": 1265.4
      },
      "eyeRightInner": {
        "x": 2867,
        "y": 1279.3
      },
      "eyeRightTop": {
        "x": 2883.8,
        "y": 1273.3
      },
      "eyeRightBottom": {
        "x": 2883.3,
        "y": 1284.2
      },
      "eyeRightOuter": {
        "x": 2900.8,
        "y": 1282.5
      },
      "noseRootLeft": {
        "x": 2815.4,
        "y": 1274.8
      },
      "noseRootRight": {
        "x": 2844.6,
        "y": 1277.7
      },
      "noseLeftAlarTop": {
        "x": 2804,
        "y": 1303.2
      },
      "noseRightAlarTop": {
        "x": 2848.9,
        "y": 1308.5
      },
      "noseLeftAlarOutTip": {
        "x": 2790.1,
        "y": 1318.6
      },
      "noseRightAlarOutTip": {
        "x": 2858.2,
        "y": 1327.6
      },
      "upperLipTop": {
        "x": 2821.9,
        "y": 1352.9
      },
      "upperLipBottom": {
        "x": 2819.4,
        "y": 1361.1
      },
      "underLipTop": {
        "x": 2817.5,
        "y": 1378.5
      },
      "underLipBottom": {
        "x": 2815.6,
        "y": 1392
      }
    },
    "faceAttributes": {
      "mask": {
        "type": "noMask",
        "noseAndMouthCovered": false
      }
    }
  }
]